{
  "id": "types/DateTime",
  "title": "DateTime",
  "description": "Class DateTime 日期和时间",
  "source": "@site/docs/types/DateTime.md",
  "sourceDirName": "types",
  "slug": "/types/DateTime",
  "permalink": "/types/DateTime",
  "draft": false,
  "unlisted": false,
  "editUrl": "https://github.com/shelllet/WinUi/edit/main/docs/types/DateTime.md",
  "tags": [],
  "version": "current",
  "frontMatter": {},
  "sidebar": "tutorialSidebar",
  "previous": {
    "title": "Contour",
    "permalink": "/types/Contour"
  },
  "next": {
    "title": "DetectionResult",
    "permalink": "/types/DetectionResult"
  }
}