{
  "id": "actions/system/CreateObject",
  "title": "创建对象",
  "description": "创建 COM 对象，或者调用创建有 c（__cdec） 接口函数的 DLL 模块. 同样也支持创建具有 __stdcall 调用约定的 DLL 模块。",
  "source": "@site/docs/actions/system/CreateObject.md",
  "sourceDirName": "actions/system",
  "slug": "/actions/system/CreateObject",
  "permalink": "/actions/system/CreateObject",
  "draft": false,
  "unlisted": false,
  "editUrl": "https://github.com/shelllet/WinUi/edit/main/docs/actions/system/CreateObject.md",
  "tags": [],
  "version": "current",
  "frontMatter": {},
  "sidebar": "tutorialSidebar",
  "previous": {
    "title": "关闭句柄",
    "permalink": "/actions/system/CloseHandle"
  },
  "next": {
    "title": "检测进程",
    "permalink": "/actions/system/ExistProcess"
  }
}