{
  "id": "types/Size",
  "title": "Size",
  "description": "Class Size， 尺寸、大小",
  "source": "@site/docs_src/types/Size.md",
  "sourceDirName": "types",
  "slug": "/types/Size",
  "permalink": "/types/Size",
  "draft": false,
  "unlisted": false,
  "editUrl": "https://github.com/shelllet/WinUi/edit/main/docs_src/types/Size.md",
  "tags": [],
  "version": "current",
  "frontMatter": {},
  "sidebar": "tutorialSidebar",
  "previous": {
    "title": "Scalar",
    "permalink": "/types/Scalar"
  },
  "next": {
    "title": "Slice",
    "permalink": "/types/Slice"
  }
}