{
  "id": "actions/draw/DrawText",
  "title": "文本绘制",
  "description": "在图像上绘制文字。",
  "source": "@site/docs_src/actions/draw/DrawText.md",
  "sourceDirName": "actions/draw",
  "slug": "/actions/draw/DrawText",
  "permalink": "/actions/draw/DrawText",
  "draft": false,
  "unlisted": false,
  "editUrl": "https://github.com/shelllet/WinUi/edit/main/docs_src/actions/draw/DrawText.md",
  "tags": [],
  "version": "current",
  "frontMatter": {},
  "sidebar": "tutorialSidebar",
  "previous": {
    "title": "绘制矩形",
    "permalink": "/actions/draw/DrawRect"
  },
  "next": {
    "title": "填充颜色",
    "permalink": "/actions/draw/FillColor"
  }
}