{
  "id": "actions/web/WebElementAttribute",
  "title": "获取属性",
  "description": "获取元素属性。",
  "source": "@site/docs_src/actions/web/WebElementAttribute.md",
  "sourceDirName": "actions/web",
  "slug": "/actions/web/WebElementAttribute",
  "permalink": "/actions/web/WebElementAttribute",
  "draft": false,
  "unlisted": false,
  "editUrl": "https://github.com/shelllet/WinUi/edit/main/docs_src/actions/web/WebElementAttribute.md",
  "tags": [],
  "version": "current",
  "frontMatter": {},
  "sidebar": "tutorialSidebar",
  "previous": {
    "title": "获取 Cookies",
    "permalink": "/actions/web/WebCookies"
  },
  "next": {
    "title": "清除文本",
    "permalink": "/actions/web/WebElementClear"
  }
}